amazon_transcribe/__init__.py
amazon_transcribe/auth.py
amazon_transcribe/client.py
amazon_transcribe/deserialize.py
amazon_transcribe/endpoints.py
amazon_transcribe/eventstream.py
amazon_transcribe/exceptions.py
amazon_transcribe/handlers.py
amazon_transcribe/httpsession.py
amazon_transcribe/model.py
amazon_transcribe/py.typed
amazon_transcribe/request.py
amazon_transcribe/response.py
amazon_transcribe/serialize.py
amazon_transcribe/signer.py
amazon_transcribe/structures.py
amazon_transcribe/utils.py
amazon_transcribe-0.6.3.dist-info/LICENSE
amazon_transcribe-0.6.3.dist-info/METADATA
amazon_transcribe-0.6.3.dist-info/NOTICE
amazon_transcribe-0.6.3.dist-info/WHEEL
amazon_transcribe-0.6.3.dist-info/top_level.txt
amazon_transcribe-0.6.3.dist-info/RECORD
